fieldoverride/__init__.py
fieldoverride/admin.py
fieldoverride/mixins.py
fieldoverride/models.py
fieldoverride/migrations/0001_initial.py
fieldoverride/migrations/__init__.py
django_admin_fieldoverride-0.3.1.dist-info/LICENSE
django_admin_fieldoverride-0.3.1.dist-info/METADATA
django_admin_fieldoverride-0.3.1.dist-info/WHEEL
django_admin_fieldoverride-0.3.1.dist-info/top_level.txt
django_admin_fieldoverride-0.3.1.dist-info/RECORD
